README.txt
setup.py
track_grabber.py
track_grabber.egg-info/PKG-INFO
track_grabber.egg-info/SOURCES.txt
track_grabber.egg-info/dependency_links.txt
track_grabber.egg-info/requires.txt
track_grabber.egg-info/top_level.txt